naidushravan_package-1.0.0.dist-info/METADATA
naidushravan_package-1.0.0.dist-info/RECORD
naidushravan_package-1.0.0.dist-info/WHEEL
naidushravan_package-1.0.0.dist-info/top_level.txt
shravan_package/__init__.py
shravan_package/shravan_package.py
